pas.plugins.kimug-1.4.0-py3.13-nspkg.pth
pas/plugins/kimug/__init__.py
pas/plugins/kimug/configure.zcml
pas/plugins/kimug/dependencies.zcml
pas/plugins/kimug/interfaces.py
pas/plugins/kimug/permissions.zcml
pas/plugins/kimug/profiles.zcml
pas/plugins/kimug/testing.py
pas/plugins/kimug/utils.py
pas/plugins/kimug/browser/configure.zcml
pas/plugins/kimug/browser/usergroups_usersoverview.pt
pas/plugins/kimug/browser/users.pt
pas/plugins/kimug/browser/view.py
pas/plugins/kimug/content/__init__.py
pas/plugins/kimug/controlpanel/__init__.py
pas/plugins/kimug/controlpanel/classic.py
pas/plugins/kimug/controlpanel/configure.zcml
pas/plugins/kimug/controlpanel/controlpanel.pt
pas/plugins/kimug/indexers/__init__.py
pas/plugins/kimug/indexers/configure.zcml
pas/plugins/kimug/locales/__init__.py
pas/plugins/kimug/locales/pas.plugins.kimug.pot
pas/plugins/kimug/locales/update.py
pas/plugins/kimug/locales/en/LC_MESSAGES/pas.plugins.kimug.po
pas/plugins/kimug/plugin/__init__.py
pas/plugins/kimug/profiles/default/browserlayer.xml
pas/plugins/kimug/profiles/default/catalog.xml
pas/plugins/kimug/profiles/default/controlpanel.xml
pas/plugins/kimug/profiles/default/diff_tool.xml
pas/plugins/kimug/profiles/default/metadata.xml
pas/plugins/kimug/profiles/default/repositorytool.xml
pas/plugins/kimug/profiles/default/rolemap.xml
pas/plugins/kimug/profiles/default/types.xml
pas/plugins/kimug/profiles/default/registry/main.xml
pas/plugins/kimug/profiles/default/types/.gitkeep
pas/plugins/kimug/profiles/uninstall/browserlayer.xml
pas/plugins/kimug/setuphandlers/__init__.py
pas/plugins/kimug/static/logo.svg
pas/plugins/kimug/subscribers/configure.zcml
pas/plugins/kimug/upgrades/__init__.py
pas/plugins/kimug/upgrades/configure.zcml
pas/plugins/kimug/vocabularies/__init__.py
pas/plugins/kimug/vocabularies/configure.zcml
pas_plugins_kimug-1.4.0.dist-info/licenses/LICENSE.GPL
pas_plugins_kimug-1.4.0.dist-info/licenses/LICENSE.md
pas_plugins_kimug-1.4.0.dist-info/METADATA
pas_plugins_kimug-1.4.0.dist-info/WHEEL
pas_plugins_kimug-1.4.0.dist-info/entry_points.txt
pas_plugins_kimug-1.4.0.dist-info/namespace_packages.txt
pas_plugins_kimug-1.4.0.dist-info/top_level.txt
pas_plugins_kimug-1.4.0.dist-info/RECORD
