Metadata-Version: 2.4
Name: pas.plugins.kimug
Version: 1.4.0
Summary: A PAS plugin to set roles to imio keycloak users
Home-page: https://github.com/imio/pas.plugins.kimug
Author: iMio
Author-email: devops@imio.be
License: GPL version 2
Project-URL: PyPI, https://pypi.org/project/pas.plugins.kimug
Project-URL: Source, https://github.com/imio/pas.plugins.kimug
Project-URL: Tracker, https://github.com/imio/pas.plugins.kimug/issues
Keywords: Python Plone CMS
Classifier: Development Status :: 3 - Alpha
Classifier: Environment :: Web Environment
Classifier: Framework :: Plone
Classifier: Framework :: Plone :: Addon
Classifier: Framework :: Plone :: 6.0
Classifier: Framework :: Plone :: 6.1
Classifier: Programming Language :: Python
Classifier: Programming Language :: Python :: 3.10
Classifier: Programming Language :: Python :: 3.11
Classifier: Programming Language :: Python :: 3.12
Classifier: Programming Language :: Python :: 3.13
Classifier: Operating System :: OS Independent
Classifier: License :: OSI Approved :: GNU General Public License v2 (GPLv2)
Requires-Python: >=3.10
License-File: LICENSE.GPL
License-File: LICENSE.md
Requires-Dist: setuptools
Requires-Dist: Products.CMFPlone
Requires-Dist: plone.api
Requires-Dist: pas.plugins.oidc>=2.0.0b4
Requires-Dist: python-keycloak
Provides-Extra: test
Requires-Dist: ipdb; extra == "test"
Requires-Dist: zest.releaser[recommended]; extra == "test"
Requires-Dist: zestreleaser.towncrier; extra == "test"
Requires-Dist: plone.app.testing; extra == "test"
Requires-Dist: plone.classicui; extra == "test"
Requires-Dist: plone.restapi[test]; extra == "test"
Requires-Dist: pytest; extra == "test"
Requires-Dist: pytest-cov; extra == "test"
Requires-Dist: pytest-plone>=0.5.0; extra == "test"
Requires-Dist: pytest-docker; extra == "test"
Dynamic: author
Dynamic: author-email
Dynamic: classifier
Dynamic: description
Dynamic: description-content-type
Dynamic: home-page
Dynamic: keywords
Dynamic: license
Dynamic: license-file
Dynamic: project-url
Dynamic: provides-extra
Dynamic: requires-dist
Dynamic: requires-python
Dynamic: summary
